{
  "1049055567": {
    "tracked": [
      {
        "username": "Jessepollak",
        "active": true,
        "ruleId": null,
        "lastChecked": "2025-04-23T12:55:14.210Z"
      },
      {
        "username": "BasedJaider",
        "active": true,
        "ruleId": null,
        "lastChecked": "2025-04-23T12:54:51.005Z"
      },
      {
        "username": "1CrypticPoet",
        "active": false,
        "ruleId": null,
        "lastChecked": null
      }
    ],
    "plan": "intermediate",
    "groupChatId": -1002513153868
  },
  "1339853448": {
    "tracked": [
      {
        "username": "BasedJaider",
        "active": false,
        "ruleId": null,
        "lastChecked": null
      }
    ],
    "plan": "premium",
    "groupChatId": -1002513153868
  }
}